agentarea/agent_kit/__init__.py
agentarea/agent_kit/example.py
agentarea/agent_kit/interfaces.py
agentarea/agent_kit/prompts.py
agentarea/agent_kit/py.typed
agentarea/agent_kit/agent_registry/agent_registry.py
agentarea/agent_kit/agents/__init__.py
agentarea/agent_kit/agents/agent.py
agentarea/agent_kit/agents/basic_agent.py
agentarea/agent_kit/agents/event_agent.py
agentarea/agent_kit/agents/multi_agent.py
agentarea/agent_kit/agents/network.py
agentarea/agent_kit/config/builtin_tools.yaml
agentarea/agent_kit/context/__init__.py
agentarea/agent_kit/context/context_service.py
agentarea/agent_kit/goal/__init__.py
agentarea/agent_kit/goal/goal_progress_evaluator.py
agentarea/agent_kit/models/__init__.py
agentarea/agent_kit/models/llm_model.py
agentarea/agent_kit/models/messages.py
agentarea/agent_kit/runners/__init__.py
agentarea/agent_kit/runners/base.py
agentarea/agent_kit/tasks/__init__.py
agentarea/agent_kit/tasks/task_service.py
agentarea/agent_kit/tasks/tasks.py
agentarea/agent_kit/tools/__init__.py
agentarea/agent_kit/tools/base_tool.py
agentarea/agent_kit/tools/builtin_tools_loader.py
agentarea/agent_kit/tools/calculate_tool.py
agentarea/agent_kit/tools/completion_tool.py
agentarea/agent_kit/tools/decorator_tool.py
agentarea/agent_kit/tools/file_toolset.py
agentarea/agent_kit/tools/handoff_tool.py
agentarea/agent_kit/tools/human_in_loop_tool.py
agentarea/agent_kit/tools/math_toolset.py
agentarea/agent_kit/tools/mcp_tool.py
agentarea/agent_kit/tools/tasks_toolset.py
agentarea/agent_kit/tools/test_tool.py
agentarea/agent_kit/tools/tool_executor.py
agentarea/agent_kit/tools/tool_manager.py
agentarea_agents_sdk-0.1.0.dist-info/METADATA
agentarea_agents_sdk-0.1.0.dist-info/WHEEL
agentarea_agents_sdk-0.1.0.dist-info/licenses/LICENSE
agentarea_agents_sdk-0.1.0.dist-info/RECORD
