Metadata-Version: 2.4
Name: agentarea-agents-sdk
Version: 0.1.0
Summary: Agent SDK for AgentArea - agentic AI components
Author-email: AgentArea <opensource@agentarea.ai>
License: MIT License
License-File: LICENSE
Keywords: agentic,agents,ai,llm,sdk
Classifier: Development Status :: 3 - Alpha
Classifier: Intended Audience :: Developers
Classifier: License :: OSI Approved :: MIT License
Classifier: Programming Language :: Python
Classifier: Programming Language :: Python :: 3
Classifier: Programming Language :: Python :: 3.11
Classifier: Programming Language :: Python :: 3.12
Classifier: Topic :: Software Development :: Libraries
Classifier: Typing :: Typed
Requires-Python: >=3.11
Requires-Dist: httpx>=0.25.0
Requires-Dist: litellm>=1.74.15
Requires-Dist: pydantic>=2.4.2
Provides-Extra: dev
Requires-Dist: mypy>=1.10.0; extra == 'dev'
Requires-Dist: pytest-asyncio>=1.0.0; extra == 'dev'
Requires-Dist: pytest-cov>=6.0.0; extra == 'dev'
Requires-Dist: pytest>=8.4.0; extra == 'dev'
Requires-Dist: ruff>=0.11.4; extra == 'dev'
